toni/__init__.py
toni-0.0.1.dist-info/LICENSE
toni-0.0.1.dist-info/WHEEL
toni-0.0.1.dist-info/METADATA
toni-0.0.1.dist-info/RECORD
