Metadata-Version: 2.1
Name: toni
Version: 0.0.1
Summary: A static site generator written in Python.
Home-page: https://github.com/vcokltfre/toni
License: MIT
Author: vcokltfre
Author-email: vcokltfre@gmail.com
Requires-Python: >=3.8,<4.0
Classifier: License :: OSI Approved :: MIT License
Classifier: Programming Language :: Python :: 3
Classifier: Programming Language :: Python :: 3.8
Classifier: Programming Language :: Python :: 3.9
Project-URL: Repository, https://github.com/vcokltfre/toni
